{"nodes": [{"id": "apps_therapist_src_utils_validators_js", "label": "validators.js", "file_type": "code", "source_file": "apps/therapist/src/utils/validators.js", "source_location": "L1"}, {"id": "validators_validateemail", "label": "validateEmail()", "file_type": "code", "source_file": "apps/therapist/src/utils/validators.js", "source_location": "L3"}, {"id": "validators_validatepassword", "label": "validatePassword()", "file_type": "code", "source_file": "apps/therapist/src/utils/validators.js", "source_location": "L10"}], "edges": [{"source": "apps_therapist_src_utils_validators_js", "target": "validators_validateemail", "relation": "contains", "confidence": "EXTRACTED", "source_file": "apps/therapist/src/utils/validators.js", "source_location": "L3", "weight": 1.0}, {"source": "apps_therapist_src_utils_validators_js", "target": "validators_validatepassword", "relation": "contains", "confidence": "EXTRACTED", "source_file": "apps/therapist/src/utils/validators.js", "source_location": "L10", "weight": 1.0}], "raw_calls": [{"caller_nid": "validators_validateemail", "callee": "trim", "source_file": "apps/therapist/src/utils/validators.js", "source_location": "L4"}, {"caller_nid": "validators_validateemail", "callee": "test", "source_file": "apps/therapist/src/utils/validators.js", "source_location": "L6"}, {"caller_nid": "validators_validatepassword", "callee": "trim", "source_file": "apps/therapist/src/utils/validators.js", "source_location": "L11"}]}